Metadata-Version: 2.1
Name: dnazip-bioinfo
Version: 0.2
Summary: A Python implementation of the Burros-Wheeler and Huffman coding algorithms
Home-page: http://github.com/dabane-ghassan/dnazip
Author: dabane-ghassan
Author-email: dabane.ghassan@gmail.com
License: MIT
Download-URL: https://github.com/dabane-ghassan/dnazip/archive/v0.2.tar.gz
Platform: UNKNOWN
Classifier: Programming Language :: Python :: 3
Classifier: License :: OSI Approved :: MIT License
Classifier: Operating System :: OS Independent
Requires-Python: >=3.6
Provides-Extra: dev
